{"name":"Rabe Abdalkareem","tagline":"","body":"#### About Me\r\nRabe Abdalkareem is a Ph.D. student at [Concordia University](https://www.concordia.ca/) supervised by [Dr. Juergen Rilling](https://sites.google.com/site/juergenrilling/)‎ and [Dr. Emad Shihab](http://users.encs.concordia.ca/~eshihab/index.html). He received his MSc. in Computer Science and Software Engineering from  Concordia university. His research interests include software engineering, software evolution and maintenance, mining software repositories, software reuse, machine learning and applications of Semantic Web in software engineering.\r\n\r\n#### Contact info.\r\nEmail: rab_abdu [at] encs [dot] concordia [dot] ca\r\n\r\n1455 De Maisonneuve Blvd. West. EV 8.150 Montreal, Quebec, Canada H3G 1M8\r\n","google":"","note":"Don't delete this file! It's used internally to help with page regeneration."}